<?xml version="1.0" encoding="utf-8"?>
<class package="BRAVO::OM" name="CustomerNumber" sql-name="customer_number">
	<property name="id" type="scalar" sql-name="customer_number_id"
		sql-key="true" />
	<property name="customerNumberId" type="scalar" equals="true"
		sql-name="customer_number_id" />
	<property name="customerId" type="scalar" equals="true"
		sql-name="customer_id" />
	<property name="customerNumber" type="scalar" equals="true"
		sql-name="customer_number" biz-key="true" />
	<property name="status" type="scalar" equals="true" sql-name="status" />
	<property name="creationDateTime" type="scalar" sql-name="creation_date_time"
		equals="true" />
	<property name="updateDateTime" type="scalar" sql-name="update_date_time"
		equals="true" />
	<property name="lpidId" type="scalar" sql-name="lpid_id"
		equals="true" />
	<property name="countryCodeId" type="scalar" sql-name="country_code_id"
		equals="true" biz-key="true" />
	<property name="action" type="scalar" equals="false" />
	<property name="table" type="scalar" default="customer_number" />
	<property name="idField" type="scalar" default="customer_number_id" />
	<method name="save" />
	<method name="delete" />
	<method name="getByBizKey" />
	<method name="getById" />
</class>
